[{"game_versions": ["1.21"], "version_number": "2.4.13", "dependencies": ["MS1ZMyR7", "3vKSKbp4", "EIa1eiMm", "P7dR8mSH", "EsAfCjCV", "mOgUt4GM", "gvQqBUqZ", "ETlrkaYF", "9s6osm5g", "YL57xq9U", "aC3cM3Vq", "HVnmMxH1", "Ha28R6CL", "l6YH9Als", "fRiHVvU7", "dLgctFID", "3IuO68q1", "lfHFW1mp", "n6PXGAoM", "5ZwdcRci", "nmDcB62a", "Eldc1g37", "Q1vvjJYV", "VSNURh3q", "OcyGmolR", "DFqQfIBR", "BVzZfTc1", "1bZhdhsH", "jULQRaG0", "nT86WUER", "OVuFYfre", "z4zsMANd", "8qkXwOnk", "Orvt0mRa", "NNAgCjsB", "R6NEzAwj", "M08ruV16", "LQ3K71Q1", "fQEb0iXm", "uXXizFIs", "1IjD5062", "xGdtZczs", "8shC1gFX", "AANobbMI"]}, {"game_versions": ["1.21"], "version_number": "2.4.12", "dependencies": ["gvQqBUqZ", "n6PXGAoM", "3IuO68q1", "OcyGmolR", "LQ3K71Q1", "3vKSKbp4", "Q1vvjJYV", "BVzZfTc1", "jULQRaG0", "xGdtZczs", "NNAgCjsB", "fQEb0iXm", "Ha28R6CL", "YL57xq9U", "M08ruV16", "uXXizFIs", "1bZhdhsH", "8qkXwOnk", "P7dR8mSH", "VSNURh3q", "5ZwdcRci", "lfHFW1mp", "nmDcB62a", "mOgUt4GM", "EIa1eiMm", "AANobbMI", "DFqQfIBR", "EsAfCjCV", null, "z4zsMANd", "aC3cM3Vq", "l6YH9Als", "8shC1gFX", "R6NEzAwj", "MS1ZMyR7", "9s6osm5g", "fRiHVvU7", "Eldc1g37", "HVnmMxH1", "dLgctFID", "OVuFYfre", "1IjD5062", "Orvt0mRa", "ETlrkaYF"]}, {"game_versions": ["1.21"], "version_number": "2.4.11", "dependencies": ["mOgUt4GM", "1bZhdhsH", "MS1ZMyR7", "l6YH9Als", "DFqQfIBR", "3vKSKbp4", "OcyGmolR", "xGdtZczs", "EIa1eiMm", "HVnmMxH1", "fQEb0iXm", "aC3cM3Vq", "dLgctFID", "5ZwdcRci", "Ha28R6CL", "fRiHVvU7", "OVuFYfre", "nmDcB62a", "lfHFW1mp", "ETlrkaYF", "3IuO68q1", "8shC1gFX", "z4zsMANd", "NNAgCjsB", "LQ3K71Q1", "YL57xq9U", "R6NEzAwj", null, "EsAfCjCV", "uXXizFIs", "Q1vvjJYV", "M08ruV16", "Eldc1g37", "AANobbMI", "9s6osm5g", "1IjD5062", "P7dR8mSH", "n6PXGAoM", "8qkXwOnk", "jULQRaG0", "gvQqBUqZ", "VSNURh3q", "Orvt0mRa"]}, {"game_versions": ["1.21"], "version_number": "2.4.10", "dependencies": ["9s6osm5g", "1bZhdhsH", "YL57xq9U", "LQ3K71Q1", "ETlrkaYF", "OVuFYfre", "n6PXGAoM", "mOgUt4GM", "gvQqBUqZ", "xGdtZczs", "lfHFW1mp", "8qkXwOnk", "R6NEzAwj", "uXXizFIs", "Ha28R6CL", "M08ruV16", "EsAfCjCV", "3IuO68q1", null, "MS1ZMyR7", "VSNURh3q", "1IjD5062", "Q1vvjJYV", "NNAgCjsB", "dLgctFID", "HVnmMxH1", "DFqQfIBR", "l6YH9Als", "Orvt0mRa", "3vKSKbp4", null, "EIa1eiMm", "Eldc1g37", "AANobbMI", "8shC1gFX", "fRiHVvU7", "OcyGmolR", "z4zsMANd", "aC3cM3Vq", "nmDcB62a", "P7dR8mSH", "fQEb0iXm", "5ZwdcRci"]}, {"game_versions": ["1.21"], "version_number": "2.4.9", "dependencies": ["1IjD5062", "8shC1gFX", "MS1ZMyR7", "ETlrkaYF", "nmDcB62a", "fRiHVvU7", "8qkXwOnk", "gvQqBUqZ", "OcyGmolR", "M08ruV16", "1bZhdhsH", "EIa1eiMm", "LQ3K71Q1", "YL57xq9U", "AANobbMI", "P7dR8mSH", "Eldc1g37", "z4zsMANd", "n6PXGAoM", "3IuO68q1", "uXXizFIs", "EsAfCjCV", "dLgctFID", "Orvt0mRa", "xGdtZczs", "VSNURh3q", "OVuFYfre", "l6YH9Als", "mOgUt4GM", "lfHFW1mp", "NNAgCjsB", "Q1vvjJYV", "Ha28R6CL", "5ZwdcRci", null, "R6NEzAwj", "aC3cM3Vq", "fQEb0iXm", "HVnmMxH1", "DFqQfIBR", "9s6osm5g"]}, {"game_versions": ["1.21"], "version_number": "2.4.8", "dependencies": ["xGdtZczs", "mOgUt4GM", "Ha28R6CL", "dLgctFID", "HVnmMxH1", "VSNURh3q", "R6NEzAwj", "z4zsMANd", "8qkXwOnk", "OVuFYfre", "8shC1gFX", "5ZwdcRci", "M08ruV16", "fRiHVvU7", "3IuO68q1", "n6PXGAoM", "9s6osm5g", "gvQqBUqZ", null, "Orvt0mRa", "nmDcB62a", "fQEb0iXm", "OcyGmolR", "l6YH9Als", "uXXizFIs", "AANobbMI", "LQ3K71Q1", "P7dR8mSH", "DFqQfIBR", "Eldc1g37", "1bZhdhsH", "Q1vvjJYV", "EIa1eiMm", "NNAgCjsB", "1IjD5062", "aC3cM3Vq", "lfHFW1mp", "YL57xq9U", "ETlrkaYF", "EsAfCjCV"]}, {"game_versions": ["1.21"], "version_number": "2.4.7", "dependencies": ["OVuFYfre", "NNAgCjsB", "gvQqBUqZ", "lfHFW1mp", "Eldc1g37", "n6PXGAoM", "fRiHVvU7", "VSNURh3q", "HVnmMxH1", "Q1vvjJYV", "9s6osm5g", "YL57xq9U", "P7dR8mSH", "8shC1gFX", "1bZhdhsH", "uXXizFIs", null, "1IjD5062", "LQ3K71Q1", "ETlrkaYF", "fQEb0iXm", "DFqQfIBR", "aC3cM3Vq", "xGdtZczs", "dLgctFID", "5ZwdcRci", "8qkXwOnk", "nmDcB62a", "mOgUt4GM", "AANobbMI", "EsAfCjCV", "Orvt0mRa", "z4zsMANd", "OcyGmolR", "EIa1eiMm", "3IuO68q1", "R6NEzAwj", "M08ruV16", "l6YH9Als", "Ha28R6CL"]}, {"game_versions": ["1.21"], "version_number": "2.4.6", "dependencies": ["z4zsMANd", "OVuFYfre", "dLgctFID", "uXXizFIs", "mOgUt4GM", "5ZwdcRci", "xGdtZczs", "1IjD5062", "gvQqBUqZ", "Q1vvjJYV", "fQEb0iXm", "HVnmMxH1", "R6NEzAwj", "M08ruV16", "P7dR8mSH", "3IuO68q1", "ETlrkaYF", "aC3cM3Vq", "EsAfCjCV", "8shC1gFX", "Ha28R6CL", "nmDcB62a", "LQ3K71Q1", "8qkXwOnk", "l6YH9Als", "lfHFW1mp", "Eldc1g37", "DFqQfIBR", "VSNURh3q", "OcyGmolR", "9s6osm5g", "NNAgCjsB", "YL57xq9U", "EIa1eiMm", "fRiHVvU7", "1bZhdhsH", "Orvt0mRa", "AANobbMI", "n6PXGAoM", null]}, {"game_versions": ["1.21"], "version_number": "2.4.5", "dependencies": ["EsAfCjCV", "3IuO68q1", "xGdtZczs", "z4zsMANd", "OVuFYfre", "Eldc1g37", "nmDcB62a", "5ZwdcRci", "OcyGmolR", "YL57xq9U", "dLgctFID", "P7dR8mSH", "VSNURh3q", "uXXizFIs", "R6NEzAwj", "Ha28R6CL", "8shC1gFX", "fQEb0iXm", "lfHFW1mp", "LQ3K71Q1", "HVnmMxH1", "aC3cM3Vq", "9s6osm5g", "1bZhdhsH", "M08ruV16", "n6PXGAoM", "AANobbMI", "fRiHVvU7", null, "Orvt0mRa", "DFqQfIBR", "mOgUt4GM", "1IjD5062", "Q1vvjJYV", "EIa1eiMm", "gvQqBUqZ", "NNAgCjsB", "8qkXwOnk"]}, {"game_versions": ["1.21"], "version_number": "2.3.4", "dependencies": ["OcyGmolR", "1bZhdhsH", "fQEb0iXm", "n6PXGAoM", "Orvt0mRa", "YL57xq9U", "lfHFW1mp", "SfMw2IZN", "EsAfCjCV", "8shC1gFX", "VSNURh3q", "HVnmMxH1", "DFqQfIBR", "mOgUt4GM", "9s6osm5g", "AANobbMI", "OVuFYfre", "fRiHVvU7", "5ZwdcRci", "Q1vvjJYV", "8qkXwOnk", "R6NEzAwj", "uXXizFIs", "dLgctFID", null, "P7dR8mSH", "xGdtZczs", "LQ3K71Q1", "Ha28R6CL", "z4zsMANd", "Eldc1g37", "NNAgCjsB", "3IuO68q1", "1IjD5062", "gvQqBUqZ"]}, {"game_versions": ["1.21"], "version_number": "2.3.2", "dependencies": ["LhlaEO2V", "n6PXGAoM", null, "8qkXwOnk", "uXXizFIs", "DFqQfIBR", null, "dLgctFID", "AANobbMI", "1IjD5062", "z4zsMANd", "9s6osm5g", "xGdtZczs", "mOgUt4GM", "YL57xq9U", "8shC1gFX", "3IuO68q1", "R6NEzAwj", "gvQqBUqZ", "P7dR8mSH", null, "LQ3K71Q1", "1bZhdhsH", "Q1vvjJYV", "Eldc1g37", "fRiHVvU7", "Ha28R6CL", "Orvt0mRa", "HVnmMxH1", "NNAgCjsB"]}, {"game_versions": ["1.21"], "version_number": "2.3.1", "dependencies": ["AANobbMI", null, "Eldc1g37", "P7dR8mSH", "gvQqBUqZ", "Orvt0mRa", "Q1vvjJYV", "9s6osm5g", "Ha28R6CL", "3IuO68q1", "xGdtZczs", "mOgUt4GM", "8shC1gFX", "DFqQfIBR", null, "1bZhdhsH", "8qkXwOnk", "R6NEzAwj", "z4zsMANd", "n6PXGAoM", "NNAgCjsB", "LhlaEO2V", "YL57xq9U", null, "HVnmMxH1", "LQ3K71Q1", "uXXizFIs", "dLgctFID", "1IjD5062"]}, {"game_versions": ["1.21"], "version_number": "2.3.0", "dependencies": ["1bZhdhsH", "z4zsMANd", "mOgUt4GM", "HVnmMxH1", "R6NEzAwj", "P7dR8mSH", "xGdtZczs", "DFqQfIBR", "Q1vvjJYV", "YL57xq9U", "AANobbMI", "LQ3K71Q1", "dLgctFID", "Ha28R6CL"]}, {"game_versions": ["1.20.6"], "version_number": "2.2.3", "dependencies": ["aru7gAyl", "DFqQfIBR", "nmDcB62a", "R6NEzAwj", "lfHFW1mp", "z4zsMANd", "YL57xq9U", "dLgctFID", "Orvt0mRa", "mOgUt4GM", "P7dR8mSH", "9s6osm5g", "1IjD5062", "uXXizFIs", "gvQqBUqZ", "HVnmMxH1", "NNAgCjsB", "M08ruV16", "8qkXwOnk", "51shyZVL", "fQEb0iXm", "1bZhdhsH", "fRiHVvU7", "xGdtZczs", "AANobbMI", "ETlrkaYF"]}, {"game_versions": ["1.20.6"], "version_number": "2.2.1", "dependencies": ["P7dR8mSH", "z4zsMANd", "NNAgCjsB", "R6NEzAwj", "lfHFW1mp", "8qkXwOnk", "51shyZVL", "9s6osm5g", "ETlrkaYF", "fQEb0iXm", "xGdtZczs", "fRiHVvU7", "mOgUt4GM", "YL57xq9U", "1bZhdhsH", "aru7gAyl", "dLgctFID", "nmDcB62a", "DFqQfIBR", "1IjD5062", "HVnmMxH1", "gvQqBUqZ", "uXXizFIs", "AANobbMI", "Orvt0mRa"]}, {"game_versions": ["1.20.6"], "version_number": "2.2.0", "dependencies": ["NNAgCjsB", "YL57xq9U", "HVnmMxH1", "aru7gAyl", "uXXizFIs", "9s6osm5g", "nmDcB62a", "mOgUt4GM", "fQEb0iXm", "gvQqBUqZ", "z4zsMANd", "1IjD5062", "DFqQfIBR", "ETlrkaYF", "51shyZVL", "1bZhdhsH", "dLgctFID", "P7dR8mSH", null, "lfHFW1mp", "Orvt0mRa", "fRiHVvU7", "AANobbMI", "8qkXwOnk", "R6NEzAwj", "xGdtZczs"]}, {"game_versions": ["1.20.5"], "version_number": "2.1.1", "dependencies": ["AANobbMI", "YL57xq9U", null, "xGdtZczs", "P7dR8mSH", "lfHFW1mp", "9s6osm5g", "51shyZVL", "uXXizFIs", "NNAgCjsB", "dLgctFID", "mOgUt4GM"]}, {"game_versions": ["1.20.5"], "version_number": "2.1.0", "dependencies": ["AANobbMI", "9s6osm5g", "dLgctFID", "xGdtZczs", "uXXizFIs", null, "lfHFW1mp", "NNAgCjsB", "mOgUt4GM", "1IjD5062", "YL57xq9U", "P7dR8mSH", "51shyZVL"]}, {"game_versions": ["1.20.5"], "version_number": "2.0.0", "dependencies": ["lfHFW1mp", "AANobbMI", null, "YL57xq9U", "xGdtZczs", "P7dR8mSH"]}, {"game_versions": ["1.20.4"], "version_number": "1.0.1", "dependencies": ["fQEb0iXm", "M08ruV16", "1IjD5062", "fRiHVvU7", "Orvt0mRa", "1bZhdhsH", "YL57xq9U", "AANobbMI", "P7dR8mSH", "dLgctFID", "gvQqBUqZ", "H8CaAYZC", "lfHFW1mp", "xGdtZczs", "uXXizFIs"]}, {"game_versions": ["1.20.4"], "version_number": "1.0.0", "dependencies": ["1IjD5062", "YL57xq9U", "uXXizFIs", "M08ruV16", "1bZhdhsH", "dLgctFID", "fRiHVvU7", "lfHFW1mp", "HVnmMxH1", "gvQqBUqZ", "AANobbMI", "R6NEzAwj", "Orvt0mRa", "fQEb0iXm", "P7dR8mSH", "xGdtZczs", "Q1vvjJYV", "H8CaAYZC"]}]