[{"game_versions": ["1.18.2"], "version_number": "0.3", "dependencies": ["P7dR8mSH", "UVtY3ZAC", "UVtY3ZAC", "nhy2KPI5", "uy4Cnpcm", "uy4Cnpcm", null, null, null, null, null, null, null, null, null, null, null, null, null, null, null, null, null, null, null, null, null, null, null, null, null, null, null, null, null, null, null, null, null, null, null, null, null, null, null, null, null, null, null, null, null, null, null, null, null, null, null, null, null, null, null, null, null, null, null, null, null, null, null, null, null, null, null, null, null, null, null, null, null, null, null, null, null, null, null, null, null, null, null, null, null, null, null, null, null, null, null, null, null, null, null, null, null, null, null, null, null, null, null, null, null, null, null, null, null, null, null, null, null, null, null, null, null, null, null, null, null, null, null, null, null, null, null, null, null]}, {"game_versions": ["1.18.2"], "version_number": "0.2", "dependencies": ["P7dR8mSH", "UVtY3ZAC", "UVtY3ZAC", "nhy2KPI5", "uy4Cnpcm", "uy4Cnpcm", null, null, null, null, null, null, null, null, null, null, null, null, null, null, null, null, null, null, null, null, null, null, null, null, null, null, null, null, null, null, null, null, null, null, null, null, null, null, null, null, null, null, null, null, null, null, null, null, null, null, null, null, null, null, null, null, null, null, null, null, null, null, null, null, null, null, null, null, null, null, null, null, null, null, null, null, null, null, null, null, null, null, null, null, null, null, null, null, null, null, null, null, null, null, null, null, null, null, null, null, null, null, null, null, null, null, null, null, null, null, null, null, null, null, null, null, null, null, null, null, null, null, null, null, null, null]}, {"game_versions": ["1.18.2"], "version_number": "0.1", "dependencies": ["YL57xq9U", "WwbubTsV", null, "LQ3K71Q1", "H8CaAYZC", null, "Ef9ZREBZ", "PtjYWJkn", null, "jsDirASn", "uLbm7CG6", "XWWYJbdG", null, "Jw3Wx1KR", null, "3hqwGCUB", "rcTfTZr3", null, null, "doqSKB0e", "BVzZfTc1", null, "Nw0MStSd", "1jvt7RTc", "NNAgCjsB", "2RKFTmiB", "XdiGl7ZL", "6jis0UTI", "AANobbMI", null, "1IjD5062", "gF3BGWvG", "63dF5mMb", "bpii4Xsa", "S5ivha5X", "mOgUt4GM", "UVtY3ZAC", "P7dR8mSH", "Nv2fQJo5", "T4Cv5iZq", "WXDvMkR5", "kYuIpRLv", "sml2FMaA", "9s6osm5g", "wcTF0Tg1", null, null, "gvQqBUqZ", "OVuFYfre", "GSw2U2lp", "R4TvILfj", "JuksLGBQ", "uPWCQrVL", "lhGA9TYQ", "DQIfKUHf", "otVJckYQ", null, "hvFnDODi", "pOQTcQmj", "w7ThoJFB", "DqIJgy14", null, null, "kqJFAPU9", "EsAfCjCV", "ojFjz7JF", null, "sUbMm93i", "uy4Cnpcm", null, "Bh37bMuy", null, "MPCX6s5C", "PRN43VSY", null, null, "G1epq3jN", "89Wsn8GD", "rqIsPf9F", "kYq5qkSL", "YOQCucah", "Ha28R6CL", "bXX9h73M", null, "yM94ont6", null, null, "uXXizFIs", "M11EPNE5", "Nz0RSWrF", "RG50cUrX", "3IuO68q1", "Orvt0mRa", "Xbc0uyRg", "8qkXwOnk", "NK39zBp2", "ohNO6lps", "ochFsQSn", null, null, "WhbRG4iK", "yBW8D80W", null, "B3HO5V57", "rUgZvGzi", "nfn13YXA", "qJDfP7WN", "iG6ZHsUV", "NRjRiSSD", "3qsfQtE9", "QwxR6Gcd", "kKwy3HU9", "Ppny3rjF", null]}]