[{"game_versions": ["1.19.2"], "version_number": "v1.1-fab1.19.2", "dependencies": ["HdwRs3kc", "m0oRwcZx", "yjgIrBjZ", "llVOZ5et", "O7JVMrQX", "ubxU84eR", "fRbqPLg4", "QwxR6Gcd", "l6YH9Als", "yF4Uptui", "rI0hvYcd", "AANobbMI", "QgxY6tZf", "wWiJfmyy", "8bcFGNZj", "NNAgCjsB", "uXXizFIs", "Bh37bMuy", "aC3cM3Vq", "H8CaAYZC", "wnEe9KBa", "YQnwl5Vv", "5ZwdcRci", "V4IQxkZC", null, "lhGA9TYQ", "PRN43VSY", "Xy8aRQKS", "Orvt0mRa", "DynYZEae", null, "2M01OLQq", "HFlxNpln", "6nAozjsh", "ZcR9weSm", "e0M1UDsY", "Hoop89kN", "b1fMg6sH", "BVzZfTc1", "MR1VIQJJ", "GiriLmaY", "hvFnDODi", "Y8uFrUil", "YL57xq9U", "yBW8D80W", "w7ThoJFB", "jg6Hhgf5", "n6PXGAoM", "rcTfTZr3", "1itdse3V", "codAaoxh", "EsAfCjCV", "rUgZvGzi", "aLcHfalx", "9s6osm5g", "WhbRG4iK", "BWloQ9jK", "5faXoLqX", "gVFdvNDw", "zV5r3pPn", "gPCdW0Wr", "k2ZPuTBm", "Wnxd13zP", "51shyZVL", "sfEDKnlo", "Ha28R6CL", "yHf7SALy", "6Hwo44S4", "OSQ8mw2r", "YOQCucah", "P7dR8mSH", "GzmTgzUV", "i090SePT", "MPCX6s5C", "1eAoo2KR", "hAt6ty93", "xp45cyDI", "mOgUt4GM", "FWumhS4T", "sGmHWmeL", "ErpAAAaf", "3IuO68q1", "mtIxmNw5", null, "iG6ZHsUV", "GtqG8z1h", "ohNO6lps", "nrJ2NpD0", "4TSI7dRt", "NRjRiSSD", "kYq5qkSL", "kYuIpRLv", "PtjYWJkn", "Kw7Sm3Xf", "T8MMXTpr", "gvQqBUqZ", "otVJckYQ", null, "wdLuzzEP", "LQ3K71Q1", "OVuFYfre", "1IjD5062", "uPWCQrVL", "gxpkKtVH", "VSNURh3q"]}, {"game_versions": ["1.19.3"], "version_number": "v2.0.1-fab1.19.3", "dependencies": ["OsZiaDHq", "Y8uFrUil", "wnEe9KBa", "Ha28R6CL", "nrJ2NpD0", "5ZwdcRci", "Hoop89kN", "BWloQ9jK", "PtjYWJkn", "T8MMXTpr", "i090SePT", "AANobbMI", "3IuO68q1", "kYq5qkSL", "lhGA9TYQ", "OSQ8mw2r", "HFlxNpln", "sfEDKnlo", "9s6osm5g", "n6PXGAoM", "rUgZvGzi", "2M01OLQq", "PRN43VSY", "fRbqPLg4", "zV5r3pPn", "VSNURh3q", "1eAoo2KR", "QdG47OkI", "mtIxmNw5", "FWumhS4T", "MPCX6s5C", "b1fMg6sH", "Wnxd13zP", "yBW8D80W", "NRjRiSSD", "P7dR8mSH", "hAt6ty93", "NNAgCjsB", "DynYZEae", "m0oRwcZx", "wdLuzzEP", "aLcHfalx", "MR1VIQJJ", "GtqG8z1h", "GiriLmaY", "gvQqBUqZ", "Orvt0mRa", "otVJckYQ", "uXXizFIs", "llVOZ5et", "ohNO6lps", "YOQCucah", "gVFdvNDw", "8bcFGNZj", "kYuIpRLv", "e0M1UDsY", "xp45cyDI", "Kw7Sm3Xf", "1itdse3V", "yF4Uptui", "mOgUt4GM", "fM515JnW", "rcTfTZr3", "k2ZPuTBm", "5faXoLqX", "yjgIrBjZ", "ErpAAAaf", "hvFnDODi", "Xy8aRQKS", "BVzZfTc1", "H8CaAYZC", "6Hwo44S4", "1OE8wbN0", "aC3cM3Vq", "ubxU84eR", "yHf7SALy", "ZcR9weSm", "rI0hvYcd", "EsAfCjCV", "jg6Hhgf5", "w7ThoJFB", "gPCdW0Wr", "51shyZVL", "l6YH9Als", "Bh37bMuy", "LQ3K71Q1", "YL57xq9U", "OVuFYfre", "gxpkKtVH", "QwxR6Gcd", "sGmHWmeL", "WhbRG4iK", "codAaoxh", "wWiJfmyy", "HdwRs3kc"]}, {"game_versions": ["1.19.2"], "version_number": "v1-fab1.19.2", "dependencies": ["5faXoLqX", "ErpAAAaf", "QgxY6tZf", "1eAoo2KR", "BVzZfTc1", "5ZwdcRci", "T8MMXTpr", "nrJ2NpD0", "aLcHfalx", "wWiJfmyy", "GtqG8z1h", "jg6Hhgf5", "kYq5qkSL", "uPWCQrVL", "H8CaAYZC", "GiriLmaY", "k2ZPuTBm", "4TSI7dRt", "NNAgCjsB", "8bcFGNZj", "Ha28R6CL", "Hoop89kN", "VSNURh3q", "ubxU84eR", "3IuO68q1", "e0M1UDsY", "rcTfTZr3", "DynYZEae", "mtIxmNw5", "PRN43VSY", "rUgZvGzi", "51shyZVL", "V4IQxkZC", "gxpkKtVH", "6Hwo44S4", "Orvt0mRa", "sfEDKnlo", "EsAfCjCV", "aC3cM3Vq", "B3HO5V57", "AANobbMI", null, "HdwRs3kc", "9s6osm5g", "lhGA9TYQ", "wnEe9KBa", "MPCX6s5C", "BWloQ9jK", "HFlxNpln", "O7JVMrQX", "PtjYWJkn", "fRbqPLg4", "1IjD5062", "2M01OLQq", "FWumhS4T", "w7ThoJFB", "kYuIpRLv", "Wnxd13zP", "yF4Uptui", "llVOZ5et", "l6YH9Als", "ohNO6lps", "sGmHWmeL", "hvFnDODi", "YQnwl5Vv", "MR1VIQJJ", null, "yHf7SALy", "6nAozjsh", "gvQqBUqZ", "i090SePT", "yBW8D80W", "ilfn0HT9", "Bh37bMuy", "b1fMg6sH", "codAaoxh", "NRjRiSSD", "P7dR8mSH", "ZcR9weSm", "LQ3K71Q1", "hAt6ty93", "WhbRG4iK", "OVuFYfre", "Kw7Sm3Xf", "uXXizFIs", "yjgIrBjZ", "rI0hvYcd", "m0oRwcZx", "wdLuzzEP", "mOgUt4GM", "iG6ZHsUV", "YOQCucah", "Y8uFrUil", "otVJckYQ", "gVFdvNDw", "QwxR6Gcd", "n6PXGAoM", "Xy8aRQKS", "1itdse3V", "YL57xq9U", "xp45cyDI", "gPCdW0Wr", "OSQ8mw2r", "zV5r3pPn"]}]