[{"game_versions": ["1.21.3"], "version_number": "1.21.3-1.0", "dependencies": ["SQKipbkd", "5ZwdcRci", "g96Z4WVZ", "VSNURh3q", "2ecVyZ49", "YL57xq9U", "wnEe9KBa", "iZ10HXDj", "4WWQxlQP", "QdG47OkI", "x9ISUf1U", "eXts2L7r", "w7ThoJFB", "89Wsn8GD", "P7dR8mSH", "UIexcMP1", "5CTSrY8X", "yBW8D80W", "AANobbMI", "LQ3K71Q1", "Ha28R6CL", "mOgUt4GM", "1eAoo2KR", "iqK5uv72"]}, {"game_versions": ["1.21.1"], "version_number": "1.21.1-1.0.0", "dependencies": ["1KiJRrTg", "8shC1gFX", "gvQqBUqZ", "iZ10HXDj", "VSNURh3q", "c7m1mi73", "ihnBJ6on", "AANobbMI", "hYykXjDp", "PtjYWJkn", "uXXizFIs", "EsAfCjCV", "SeCuopwJ", "LMIZZNxZ", "9mtu0sUO", "89Wsn8GD", "4das1Fjq", "2M01OLQq", "BdW3SxnX", "uLbm7CG6", "1u6JkXh5", "U1hgptta", "blWBX5n1", "WNcgffMw", "1IjD5062", "QdG47OkI", "BVzZfTc1", "nmDcB62a", "RSeLon5O", "9s6osm5g", "onSQdWhM", "wdLuzzEP", "rIC2XJV4", "4I1XuqiY", "yfDziwn1", "3s19I5jr", "RLzHAoZe", "Bh37bMuy", "BrRak9pu", "2ecVyZ49", "O7RBXm3n", "9eGKb6K1", "Orvt0mRa", "Ha28R6CL", "AghHBZC5", "g96Z4WVZ", "5ZwdcRci", "SQKipbkd", "NNAgCjsB", "R6NEzAwj", "YL57xq9U", "P7dR8mSH", "LQ3K71Q1", "mOgUt4GM"]}, {"game_versions": ["1.21.1"], "version_number": "0.2.0", "dependencies": ["2ecVyZ49", "rIC2XJV4", "8shC1gFX", "onSQdWhM", "c7m1mi73", "1IjD5062", "g96Z4WVZ", "VSNURh3q", "1KiJRrTg", "EsAfCjCV", "5ZwdcRci", "LQ3K71Q1", null, "O7RBXm3n", "Orvt0mRa", "wdLuzzEP", "9s6osm5g", "P7dR8mSH", "yfDziwn1", "mOgUt4GM", "BdW3SxnX", "1u6JkXh5", "YL57xq9U", "4I1XuqiY", "Ha28R6CL", "2M01OLQq", "Bh37bMuy", "BrRak9pu", "LMIZZNxZ", "R6NEzAwj", "uXXizFIs", "nmDcB62a", "89Wsn8GD", "ihnBJ6on", "k2ZPuTBm", "PtjYWJkn", "blWBX5n1", "iZ10HXDj", "RLzHAoZe", "uLbm7CG6", "AANobbMI", "BVzZfTc1"]}, {"game_versions": ["1.21.1"], "version_number": "0.1.0", "dependencies": ["uLbm7CG6", "R6NEzAwj", "AANobbMI", "EsAfCjCV", "BrRak9pu", "nmDcB62a", "P7dR8mSH", "LQ3K71Q1", "5ZwdcRci", "Bh37bMuy", "4I1XuqiY", "Ha28R6CL", "g96Z4WVZ", "LMIZZNxZ", "YL57xq9U", "k2ZPuTBm", "yfDziwn1", "BVzZfTc1", "iZ10HXDj", "c7m1mi73", "PtjYWJkn", "mOgUt4GM", "ihnBJ6on", "RLzHAoZe"]}, {"game_versions": ["1.21"], "version_number": "1.5.0", "dependencies": ["nmDcB62a", "Bh37bMuy", "GNxdLCoP", "gvQqBUqZ", null, "yjgIrBjZ", "iqK5uv72", "3qsfQtE9", "2M01OLQq", "blWBX5n1", "89Wsn8GD", "PtjYWJkn", "g96Z4WVZ", "izsIPI7a", "P7dR8mSH", "Q1vvjJYV", "l6YH9Als", "trr0scVt", "9pxxsRjM", "YL57xq9U", "Nv2fQJo5", "EsAfCjCV", "RfFxanNh", "XeEZ3fK2", "ZP7xHXtw", "OVuFYfre", "qANg5Jrr", "PiuygVWJ", "NK39zBp2", "uLbm7CG6", "2ecVyZ49", "YBz7DOs8", "onSQdWhM", "x9ISUf1U", "mOgUt4GM", "SfMw2IZN", "I70N6bTC", "wnEe9KBa", "Ha28R6CL", "LVTZtqlk", "kmwfVOoi", "sGmHWmeL", "1IjD5062", "NNAgCjsB", "uXXizFIs", "5lvjfaRs", "iZ10HXDj", "5ZwdcRci", "KuNKN7d2", "8qkXwOnk", "vevAjqG0", "wdLuzzEP", "yfDziwn1", "AANobbMI", "1eAoo2KR", "rIC2XJV4", "BVzZfTc1", "w7ThoJFB", "HpdHOPOp", "4I1XuqiY", "M08ruV16", "R6NEzAwj", "Orvt0mRa", "SQKipbkd", "k2ZPuTBm", "O7RBXm3n", "QdG47OkI", "xUTHly0N", "9s6osm5g", "c7m1mi73", "RLzHAoZe", "codAaoxh"]}, {"game_versions": ["1.21"], "version_number": "1.4.0", "dependencies": [null, "8qkXwOnk", "x9ISUf1U", "9mtu0sUO", "OVuFYfre", "g96Z4WVZ", "NK39zBp2", "gvQqBUqZ", "onSQdWhM", "9pxxsRjM", "wdLuzzEP", "M08ruV16", "yfDziwn1", "P7dR8mSH", "2ecVyZ49", "9s6osm5g", "5lvjfaRs", "xUTHly0N", "RfFxanNh", "ZP7xHXtw", "O7RBXm3n", "Bh37bMuy", "c7m1mi73", "uLbm7CG6", "sGmHWmeL", "izsIPI7a", "SQKipbkd", "rIC2XJV4", "trr0scVt", "EsAfCjCV", "NNAgCjsB", "YBz7DOs8", "4I1XuqiY", "vevAjqG0", "Q1vvjJYV", "YL57xq9U", "AANobbMI", "R6NEzAwj", "qANg5Jrr", "codAaoxh", "XeEZ3fK2", "k2ZPuTBm", "LVTZtqlk", "BVzZfTc1", "nmDcB62a", "1IjD5062", "uXXizFIs", "GNxdLCoP", "Ha28R6CL", "89Wsn8GD", "iZ10HXDj", "HpdHOPOp", "PtjYWJkn", "5ZwdcRci", "mOgUt4GM", "Orvt0mRa", "w7ThoJFB", "wnEe9KBa", "SfMw2IZN", "RLzHAoZe", "2M01OLQq", "yjgIrBjZ", "1eAoo2KR", "blWBX5n1", "QdG47OkI"]}, {"game_versions": ["1.21"], "version_number": "1.3.0.1", "dependencies": ["NNAgCjsB", "Orvt0mRa", "BVzZfTc1", "Bh37bMuy", "8qkXwOnk", "RfFxanNh", "AANobbMI", "Q1vvjJYV", "yjgIrBjZ", "sGmHWmeL", "izsIPI7a", "onSQdWhM", "blWBX5n1", "YBz7DOs8", "wdLuzzEP", "89Wsn8GD", "uXXizFIs", "x9ISUf1U", "9pxxsRjM", "1IjD5062", "5lvjfaRs", "iZ10HXDj", "FimwF33K", "LVTZtqlk", "gvQqBUqZ", "vevAjqG0", "9mtu0sUO", "qANg5Jrr", "wnEe9KBa", "c7m1mi73", "O7RBXm3n", "SQKipbkd", "yfDziwn1", "1eAoo2KR", "R6NEzAwj", "NK39zBp2", "w7ThoJFB", "codAaoxh", "ZP7xHXtw", "rIC2XJV4", "GNxdLCoP", "4I1XuqiY", "uLbm7CG6", "9s6osm5g", "PtjYWJkn", "5ZwdcRci", "g96Z4WVZ", "Ha28R6CL", "P7dR8mSH", null, "2ecVyZ49", "xUTHly0N", "HpdHOPOp", "k2ZPuTBm", "nmDcB62a", "mOgUt4GM", "YL57xq9U", "2M01OLQq", "OVuFYfre", "QdG47OkI", "trr0scVt", "EsAfCjCV"]}, {"game_versions": ["1.21"], "version_number": "1.2.5", "dependencies": ["trr0scVt", "nmDcB62a", "4I1XuqiY", "ZP7xHXtw", "5lvjfaRs", "wnEe9KBa", "AANobbMI", "w7ThoJFB", "onSQdWhM", "9s6osm5g", "LVTZtqlk", "xUTHly0N", "RfFxanNh", "P7dR8mSH", "Orvt0mRa", "QdG47OkI", "89Wsn8GD", "HpdHOPOp", "codAaoxh", "c7m1mi73", "wdLuzzEP", "gvQqBUqZ", "Bh37bMuy", "NK39zBp2", "9pxxsRjM", "mOgUt4GM", "1eAoo2KR", "x9ISUf1U", "uXXizFIs", "Q1vvjJYV", "Ha28R6CL", "iZ10HXDj", "YBz7DOs8", "2ecVyZ49", "R6NEzAwj", "1IjD5062", "O7RBXm3n", "SQKipbkd", "uLbm7CG6", null, "izsIPI7a", "NNAgCjsB", "blWBX5n1", "YL57xq9U", "iqK5uv72", "PtjYWJkn", "EsAfCjCV", "5ZwdcRci", "BVzZfTc1", "sGmHWmeL", "yfDziwn1", "k2ZPuTBm", "g96Z4WVZ", "rIC2XJV4", "OVuFYfre"]}, {"game_versions": ["1.21"], "version_number": "1.2.0", "dependencies": ["9pxxsRjM", "RfFxanNh", "HpdHOPOp", "4I1XuqiY", "LVTZtqlk", "1eAoo2KR", "nmDcB62a", "sGmHWmeL", "ZP7xHXtw", "YL57xq9U", "trr0scVt", "9s6osm5g", "xUTHly0N", "codAaoxh", "onSQdWhM", "blWBX5n1", "uLbm7CG6", "izsIPI7a", "PtjYWJkn", "wnEe9KBa", "AANobbMI", "wdLuzzEP", "gvQqBUqZ", "BVzZfTc1", "O7RBXm3n", "iqK5uv72", "OVuFYfre", "yfDziwn1", "k2ZPuTBm", "R6NEzAwj", "Ha28R6CL", "2ecVyZ49", "iZ10HXDj", "Bh37bMuy", "Q1vvjJYV", "c7m1mi73", "Orvt0mRa", "5lvjfaRs", "YBz7DOs8", "g96Z4WVZ", null, "EsAfCjCV", "uXXizFIs", "mOgUt4GM", "1IjD5062", "P7dR8mSH", "rIC2XJV4", "w7ThoJFB", "NK39zBp2", "NNAgCjsB", "5ZwdcRci"]}, {"game_versions": ["1.21"], "version_number": "1.1.0", "dependencies": ["izsIPI7a", "YL57xq9U", "Orvt0mRa", "Q1vvjJYV", "g96Z4WVZ", "c7m1mi73", null, "xUTHly0N", "9pxxsRjM", "ZP7xHXtw", "2ecVyZ49", "wnEe9KBa", "1IjD5062", "AANobbMI", "BVzZfTc1", "5ZwdcRci", "HpdHOPOp", "PtjYWJkn", "uXXizFIs", "sGmHWmeL", "uLbm7CG6", "iqK5uv72", "9s6osm5g", "trr0scVt", "4I1XuqiY", "8bOImuGU", "LVTZtqlk", "YBz7DOs8", "NNAgCjsB", "5lvjfaRs", "mOgUt4GM", "k2ZPuTBm", "wdLuzzEP", "blWBX5n1", "R6NEzAwj", "RfFxanNh", "P7dR8mSH", "iZ10HXDj", "codAaoxh", "nmDcB62a", "OVuFYfre", "yfDziwn1", "EsAfCjCV", "gvQqBUqZ", "Bh37bMuy"]}, {"game_versions": ["1.21"], "version_number": "1.0.11", "dependencies": ["iZ10HXDj", "wnEe9KBa", "iqK5uv72", "wdLuzzEP", "trr0scVt", "g96Z4WVZ", "sGmHWmeL", "OVuFYfre", "R6NEzAwj", "nmDcB62a", "uLbm7CG6", "YL57xq9U", "P7dR8mSH", "8bOImuGU", "Q1vvjJYV", "YBz7DOs8", "Bh37bMuy", "blWBX5n1", "1IjD5062", "9pxxsRjM", "AANobbMI", "PtjYWJkn", "9s6osm5g", "mOgUt4GM", "yfDziwn1", null, "4I1XuqiY", "codAaoxh", "BVzZfTc1", "5lvjfaRs", "NNAgCjsB", "5ZwdcRci", "xUTHly0N", "k2ZPuTBm", "HpdHOPOp", "ZP7xHXtw", "c7m1mi73", "izsIPI7a", "2ecVyZ49"]}, {"game_versions": ["1.21"], "version_number": "1.0.11", "dependencies": ["1IjD5062", "2ecVyZ49", "4I1XuqiY", "5ZwdcRci", "5lvjfaRs", "8bOImuGU", "9pxxsRjM", "9s6osm5g", "AANobbMI", "BVzZfTc1", "Bh37bMuy", "HpdHOPOp", "NNAgCjsB", "OVuFYfre", "P7dR8mSH", "PtjYWJkn", "Q1vvjJYV", "R6NEzAwj", "YBz7DOs8", "YL57xq9U", "ZP7xHXtw", "blWBX5n1", "c7m1mi73", "codAaoxh", "g96Z4WVZ", "iZ10HXDj", "iqK5uv72", "izsIPI7a", "k2ZPuTBm", "mOgUt4GM", "nmDcB62a", "sGmHWmeL", "trr0scVt", "uLbm7CG6", "wdLuzzEP", "wnEe9KBa", "xUTHly0N", "yfDziwn1"]}]