[{"game_versions": ["1.20.1"], "version_number": "0.0.2", "dependencies": ["TqCKvqjC", "HnD1GX6e", "sk9knFPE", "kidLKymU", "4EakbH8e", "fThnVRli", "GyKzAh3l", "XxWD5pD3", "nU0bVIaL", "1eAoo2KR", "pNabrMMw", "ZYgyPyfq", "u6dRKJwZ", "2BwBOmBQ", "9eGKb6K1", "v3CYg2V9", "jv0UKGOX", "mPND0Adp", "BAscRYKm", "CVT4pFB2", "Xbc0uyRg", "l6YH9Als", "ZzjhlDgM", "J81TRJWm", "4XJZeZbM", "QAGBst4M", "mOgUt4GM", "9s6osm5g", "b1ZV3DIJ", "Ha28R6CL", "umyGl7zF", "vE2FN5qn", "EO8aSHxh", "aC3cM3Vq", "Wq5SjeWM", "QwxR6Gcd", "gF3BGWvG", "z9Ve58Ih", "kU1G12Nn", "1DWmBJVA", "yM94ont6", "sMvUb4Rb", "Ua7DFN59", "w7ThoJFB", "6txNkua3", "WFwYiVoG", "jmJ87gsb", "reiRz8zO", "lhGA9TYQ", "gJ5afkVv", "t5W7Jfwy", "1bokaNcj", "16DuAG4k", "Mn8ziD0c", "T4Cv5iZq", "AhtxbnpG", "rlloIFEV", "V5ujR2yw", "EsAfCjCV", "NRjRiSSD", "LQ3K71Q1", "nvQzSEkH", "UT2M39wf", "NcUtCpym", "Z2mXHnxP", "GWp4jCJj", "G1hIVOrD", "Wnxd13zP", "5ZwdcRci", "K01OU20C", "Cw8IlnGM", "ZGaA9I33", "P7dR8mSH", "XNlO7sBv"]}, {"game_versions": ["1.20.1"], "version_number": "0.0.1", "dependencies": ["ZGaA9I33", "Mn8ziD0c", "kidLKymU", "2BwBOmBQ", "Xbc0uyRg", "sk9knFPE", "lhGA9TYQ", "4EakbH8e", "QAGBst4M", "NRjRiSSD", "mOgUt4GM", "v3CYg2V9", "EO8aSHxh", "1bokaNcj", "rlloIFEV", "pNabrMMw", "Z2mXHnxP", "AhtxbnpG", "mPND0Adp", "HnD1GX6e", "P7dR8mSH", "1DWmBJVA", "sMvUb4Rb", "reiRz8zO", "ZzjhlDgM", "G1hIVOrD", "CVT4pFB2", "z9Ve58Ih", "GyKzAh3l", "Cw8IlnGM", "LQ3K71Q1", "XxWD5pD3", "BAscRYKm", "16DuAG4k", "5ZwdcRci", "UT2M39wf", "NcUtCpym", "fThnVRli", "t5W7Jfwy", "b1ZV3DIJ", "Wnxd13zP", "nvQzSEkH", "jmJ87gsb", "Ha28R6CL", "umyGl7zF", "9eGKb6K1", "w7ThoJFB", "WFwYiVoG", "gF3BGWvG", "nU0bVIaL", "EsAfCjCV", "aC3cM3Vq", "QwxR6Gcd", "Ua7DFN59", "1eAoo2KR", "J81TRJWm", "jv0UKGOX", "4XJZeZbM", "Wq5SjeWM", "V5ujR2yw", "ZYgyPyfq", "yM94ont6", "T4Cv5iZq", "GWp4jCJj", "9s6osm5g", "K01OU20C", "6txNkua3", "u6dRKJwZ", "XNlO7sBv", "vE2FN5qn", "TqCKvqjC", "kU1G12Nn", "gJ5afkVv"]}, {"game_versions": ["1.20.1"], "version_number": "1.1.1", "dependencies": ["LQ3K71Q1", "kidLKymU", "nFIzW822", "9s6osm5g", "nvQzSEkH", "qyVF9oeo", "Ua7DFN59", "4EakbH8e", "K01OU20C", "Mn8ziD0c", "Xbc0uyRg", "jmJ87gsb", "Wq5SjeWM", "ssUbhMkL", "1DWmBJVA", "kU1G12Nn", "BAscRYKm", "fThnVRli", "XNlO7sBv", "ZGaA9I33", "reiRz8zO", "TqCKvqjC", "ZYgyPyfq", null, "yM94ont6", "pNabrMMw", "rlloIFEV", "nU0bVIaL", "AhtxbnpG", "sk9knFPE", "w7ThoJFB", "1eAoo2KR", "G1hIVOrD", "jv0UKGOX", "gJ5afkVv", "mPND0Adp", "2BwBOmBQ", "Wnxd13zP", "Z2mXHnxP", "4XJZeZbM", "nELKzJ5C", "Cw8IlnGM", "mOgUt4GM", "NcUtCpym", "NRjRiSSD", "GyKzAh3l", "EO8aSHxh", "aC3cM3Vq", "gF3BGWvG", "EsAfCjCV", "T4Cv5iZq", "V5ujR2yw", "WFwYiVoG", "5ZwdcRci", "16DuAG4k", "umyGl7zF", "lhGA9TYQ", "P7dR8mSH", "z9Ve58Ih", "J81TRJWm", "QwxR6Gcd", "1bokaNcj", "Ha28R6CL", "t5W7Jfwy", "XxWD5pD3", "6txNkua3", "MyfCcqiE", "u6dRKJwZ", "ZzjhlDgM", "GWp4jCJj", "ItHr72Fy", "v3CYg2V9", "QAGBst4M", "5aaWibi9", "b1ZV3DIJ", "sMvUb4Rb", "CVT4pFB2", "9eGKb6K1"]}, {"game_versions": ["1.20.1"], "version_number": "1.1.0", "dependencies": ["BAscRYKm", "NRjRiSSD", "T4Cv5iZq", "2BwBOmBQ", "4XJZeZbM", "NcUtCpym", "K01OU20C", "V5ujR2yw", null, "u6dRKJwZ", "nvQzSEkH", "reiRz8zO", "ssUbhMkL", "kidLKymU", "lhGA9TYQ", "gF3BGWvG", "LQ3K71Q1", "fThnVRli", "t5W7Jfwy", "jv0UKGOX", "4EakbH8e", "ZYgyPyfq", "w7ThoJFB", "rlloIFEV", "Mn8ziD0c", "sMvUb4Rb", "umyGl7zF", "v3CYg2V9", "5ZwdcRci", "16DuAG4k", "Ua7DFN59", "nFIzW822", "XxWD5pD3", "jmJ87gsb", "GyKzAh3l", "gJ5afkVv", "nU0bVIaL", "XNlO7sBv", "6txNkua3", "1DWmBJVA", "5aaWibi9", "TqCKvqjC", "1eAoo2KR", "QAGBst4M", "Z2mXHnxP", "Wq5SjeWM", "9eGKb6K1", "Xbc0uyRg", "QwxR6Gcd", "nELKzJ5C", "EO8aSHxh", "sk9knFPE", "GWp4jCJj", "Cw8IlnGM", "AhtxbnpG", "CVT4pFB2", "WFwYiVoG", "ZzjhlDgM", "P7dR8mSH", "1bokaNcj", "G1hIVOrD", "z9Ve58Ih", "MyfCcqiE", "mPND0Adp", "EsAfCjCV", "mOgUt4GM", "aC3cM3Vq", "ZGaA9I33", "b1ZV3DIJ", "Ha28R6CL", "J81TRJWm", "pNabrMMw", "Wnxd13zP", "ItHr72Fy", "kU1G12Nn", "qyVF9oeo", "9s6osm5g"]}, {"game_versions": ["1.20.1"], "version_number": "1.0.9", "dependencies": ["jv0UKGOX", "1eAoo2KR", "1bokaNcj", "ZYgyPyfq", "BAscRYKm", "sMvUb4Rb", "ZGaA9I33", "rlloIFEV", "Wnxd13zP", "gF3BGWvG", "5ZwdcRci", "lhGA9TYQ", "16DuAG4k", "QwxR6Gcd", "NRjRiSSD", "4EakbH8e", "CVT4pFB2", "kU1G12Nn", "V5ujR2yw", "1DWmBJVA", "z9Ve58Ih", "qyVF9oeo", "b1ZV3DIJ", "v3CYg2V9", "Wq5SjeWM", "w7ThoJFB", "WFwYiVoG", "ssUbhMkL", "nvQzSEkH", "6txNkua3", "Ha28R6CL", "T4Cv5iZq", "jmJ87gsb", "MyfCcqiE", "K01OU20C", "EsAfCjCV", "LQ3K71Q1", "reiRz8zO", "J81TRJWm", "fThnVRli", "t5W7Jfwy", "XxWD5pD3", "pNabrMMw", "8pcjMDgj", "TqCKvqjC", "gJ5afkVv", "Mn8ziD0c", "ZzjhlDgM", "kidLKymU", "Xbc0uyRg", "aC3cM3Vq", "P7dR8mSH", "u6dRKJwZ", "cV5LQXKx", null, "sk9knFPE", "nELKzJ5C", "9eGKb6K1", "AhtxbnpG", "G1hIVOrD", "mPND0Adp", "5aaWibi9", "2BwBOmBQ", "EO8aSHxh", "QAGBst4M", "GWp4jCJj", "Cw8IlnGM", "Ua7DFN59", "4XJZeZbM", "GyKzAh3l", "NcUtCpym", "Z2mXHnxP", "umyGl7zF", "XNlO7sBv"]}, {"game_versions": ["1.20.1"], "version_number": "1.0.8", "dependencies": ["nvQzSEkH", "fThnVRli", "ssUbhMkL", "reiRz8zO", "sMvUb4Rb", "1eAoo2KR", "u6dRKJwZ", "8pcjMDgj", "WFwYiVoG", "jv0UKGOX", "K01OU20C", "nELKzJ5C", "NcUtCpym", "mPND0Adp", "aC3cM3Vq", "5aaWibi9", "t5W7Jfwy", "qyVF9oeo", "4EakbH8e", "umyGl7zF", "rlloIFEV", "lhGA9TYQ", "w7ThoJFB", "XNlO7sBv", "ZYgyPyfq", "2BwBOmBQ", "Wnxd13zP", "1DWmBJVA", "P7dR8mSH", "CVT4pFB2", "cV5LQXKx", "EO8aSHxh", "v3CYg2V9", "V5ujR2yw", "4XJZeZbM", "QwxR6Gcd", "z9Ve58Ih", "TqCKvqjC", "Z2mXHnxP", "MyfCcqiE", "T4Cv5iZq", "16DuAG4k", "5ZwdcRci", "AhtxbnpG", "XxWD5pD3", "gF3BGWvG", "Xbc0uyRg", "GWp4jCJj", null, "LQ3K71Q1", "jmJ87gsb", "NRjRiSSD", "BAscRYKm", "kidLKymU", "6txNkua3", "J81TRJWm", "Ha28R6CL", "G1hIVOrD", "gJ5afkVv", "ZzjhlDgM", "1bokaNcj", "9eGKb6K1", "Ua7DFN59", "sk9knFPE", "QAGBst4M", "GyKzAh3l", "kU1G12Nn", "b1ZV3DIJ", "ZGaA9I33", "pNabrMMw", "Cw8IlnGM", "EsAfCjCV", "Wq5SjeWM"]}, {"game_versions": ["1.20.1"], "version_number": "1.0.7", "dependencies": ["sMvUb4Rb", "2BwBOmBQ", "5aaWibi9", "rlloIFEV", "1DWmBJVA", "1eAoo2KR", "Wnxd13zP", "CVT4pFB2", "gJ5afkVv", "BAscRYKm", "4EakbH8e", "GyKzAh3l", "8pcjMDgj", "v3CYg2V9", "NRjRiSSD", "GWp4jCJj", "Ua7DFN59", "lhGA9TYQ", "z9Ve58Ih", "1bokaNcj", "pNabrMMw", "LQ3K71Q1", "w7ThoJFB", "ZYgyPyfq", "jmJ87gsb", "9eGKb6K1", "QAGBst4M", "MyfCcqiE", "umyGl7zF", "t5W7Jfwy", "ZGaA9I33", "nvQzSEkH", "Ha28R6CL", "QwxR6Gcd", "Z2mXHnxP", "5ZwdcRci", "nELKzJ5C", "6txNkua3", "jv0UKGOX", "fThnVRli", "Cw8IlnGM", "WFwYiVoG", "NcUtCpym", "ZzjhlDgM", "V5ujR2yw", "P7dR8mSH", "G1hIVOrD", "AhtxbnpG", "kidLKymU", "J81TRJWm", "ssUbhMkL", "4XJZeZbM", "sk9knFPE", "Wq5SjeWM", null, "XNlO7sBv", "kU1G12Nn", "K01OU20C", "mPND0Adp", "cV5LQXKx", "Xbc0uyRg", "XxWD5pD3", "TqCKvqjC", "aC3cM3Vq", "reiRz8zO", "16DuAG4k", "gF3BGWvG", "b1ZV3DIJ", "qyVF9oeo", "EsAfCjCV", "u6dRKJwZ", "T4Cv5iZq"]}, {"game_versions": ["1.20.1"], "version_number": "1.0.6", "dependencies": ["kU1G12Nn", "mPND0Adp", "ssUbhMkL", "Z2mXHnxP", "Wnxd13zP", "reiRz8zO", "rlloIFEV", "MyfCcqiE", "TqCKvqjC", "CVT4pFB2", "QAGBst4M", "6txNkua3", "EsAfCjCV", "5aaWibi9", "NcUtCpym", "4XJZeZbM", "4EakbH8e", "nvQzSEkH", "ZzjhlDgM", "G1hIVOrD", "pNabrMMw", "lhGA9TYQ", "2BwBOmBQ", "cV5LQXKx", "1bokaNcj", "sk9knFPE", "WFwYiVoG", "t5W7Jfwy", "P7dR8mSH", "jmJ87gsb", "1eAoo2KR", "1DWmBJVA", "GyKzAh3l", "kidLKymU", "z9Ve58Ih", "b1ZV3DIJ", "AhtxbnpG", "XxWD5pD3", "8pcjMDgj", "gJ5afkVv", "XNlO7sBv", "gF3BGWvG", "v3CYg2V9", "u6dRKJwZ", "V5ujR2yw", "nELKzJ5C", "aC3cM3Vq", "w7ThoJFB", "umyGl7zF", "J81TRJWm", "Xbc0uyRg", "5ZwdcRci", "Ua7DFN59", "K01OU20C", "qyVF9oeo", "LQ3K71Q1", "NRjRiSSD", "BAscRYKm", "ZGaA9I33", "T4Cv5iZq", "Ha28R6CL", "fThnVRli", "ZYgyPyfq", "Wq5SjeWM", "jv0UKGOX", "sMvUb4Rb"]}, {"game_versions": ["1.20.1"], "version_number": "1.0.5", "dependencies": ["J81TRJWm", "ZGaA9I33", "NRjRiSSD", "kidLKymU", "v3CYg2V9", "gF3BGWvG", "cV5LQXKx", "Z2mXHnxP", "LQ3K71Q1", "b1ZV3DIJ", "nELKzJ5C", "Wq5SjeWM", "reiRz8zO", "MyfCcqiE", "T4Cv5iZq", "4XJZeZbM", "ZzjhlDgM", "P7dR8mSH", "K01OU20C", "umyGl7zF", "nvQzSEkH", "z9Ve58Ih", "6txNkua3", "V5ujR2yw", "t5W7Jfwy", "jmJ87gsb", "QAGBst4M", "gJ5afkVv", "Xbc0uyRg", "5aaWibi9", "Wnxd13zP", "jv0UKGOX", "2BwBOmBQ", "rlloIFEV", "qyVF9oeo", "WFwYiVoG", "EsAfCjCV", "sMvUb4Rb", "1bokaNcj", "G1hIVOrD", "BAscRYKm", "sk9knFPE", "ssUbhMkL", "5ZwdcRci", "pNabrMMw", "u6dRKJwZ", "4EakbH8e", "XNlO7sBv", "kU1G12Nn", "lhGA9TYQ", "Ua7DFN59", "1DWmBJVA", "TqCKvqjC", "XxWD5pD3", "AhtxbnpG", "CVT4pFB2", "ZYgyPyfq", "8pcjMDgj", "GyKzAh3l", "NcUtCpym", "fThnVRli", "mPND0Adp", "aC3cM3Vq"]}]